obs/__init__.py
obs/admin.py
obs/models.py
obs/plugin.py
obs/urls.py
obs/views.py
obs/migrations/0001_initial.py
obs/migrations/0002_observation_episode.py
obs/migrations/0003_auto_20150918_1516.py
obs/migrations/0004_auto_20181114_1424.py
obs/migrations/__init__.py
obs/static/js/obs/controllers/obs_chart.js
obs/static/js/obs/services/records/observation.js
obs/static/js/test/obs_chart.test.js
obs/static/js/test/observation.record.test.js
obs/templates/forms/observation_form.html
obs/templates/obs/chart.html
obs/templates/obs/detail_panel.html
obs/templates/records/observation.html
obs/tests/__init__.py
obs/tests/dummy_options_module.py
obs/tests/test_views.py
opal_observations-0.5.0.dist-info/LICENSE.md
opal_observations-0.5.0.dist-info/METADATA
opal_observations-0.5.0.dist-info/WHEEL
opal_observations-0.5.0.dist-info/top_level.txt
opal_observations-0.5.0.dist-info/RECORD
