Metadata-Version: 2.1
Name: opal-observations
Version: 0.5.0
Summary: Opal Plugin for observations
Home-page: http://opal.openhealthcare.org.uk/
Author: Open Health Care UK
Author-email: hello@openhealthcare.org.uk
License: GPL3
Platform: UNKNOWN
